msgraph/__init__.py
msgraph/msgraph.py
msgraph_pywrap-0.1.3.dist-info/METADATA
msgraph_pywrap-0.1.3.dist-info/WHEEL
msgraph_pywrap-0.1.3.dist-info/top_level.txt
msgraph_pywrap-0.1.3.dist-info/RECORD
