Metadata-Version: 2.4
Name: msgraph-pywrap
Version: 0.1.3
Summary: Utility for abstracting connections to Microsoft's Graph API and Sharepoint.
Author-email: Johanes Killan Berto Alves <killanalvesj@gmail.com>
License: MIT
Project-URL: Homepage, https://github.com/killanj/project-msgraph
Project-URL: Repository, https://github.com/killanj/project-msgraph
Project-URL: Issues, https://github.com/killanj/project-msgraph/issues
Keywords: microsoft-graph,sharepoint,api,msgraph,upload,automation
Classifier: Development Status :: 3 - Alpha
Classifier: Programming Language :: Python :: 3
Classifier: License :: OSI Approved :: MIT License
Classifier: Operating System :: OS Independent
Requires-Python: >=3.10
Requires-Dist: requests>=2.32.3
